MANIFEST.in
README.md
meta.json
setup.py
en_ud_model/__init__.py
en_ud_model/meta.json
en_ud_model.egg-info/PKG-INFO
en_ud_model.egg-info/SOURCES.txt
en_ud_model.egg-info/dependency_links.txt
en_ud_model.egg-info/not-zip-safe
en_ud_model.egg-info/requires.txt
en_ud_model.egg-info/top_level.txt
en_ud_model/en_ud_model-1.1.0/meta.json
en_ud_model/en_ud_model-1.1.0/tokenizer
en_ud_model/en_ud_model-1.1.0/ner/cfg
en_ud_model/en_ud_model-1.1.0/ner/model
en_ud_model/en_ud_model-1.1.0/ner/moves
en_ud_model/en_ud_model-1.1.0/parser/cfg
en_ud_model/en_ud_model-1.1.0/parser/model
en_ud_model/en_ud_model-1.1.0/parser/moves
en_ud_model/en_ud_model-1.1.0/tagger/cfg
en_ud_model/en_ud_model-1.1.0/tagger/model
en_ud_model/en_ud_model-1.1.0/tagger/tag_map
en_ud_model/en_ud_model-1.1.0/vocab/key2row
en_ud_model/en_ud_model-1.1.0/vocab/lexemes.bin
en_ud_model/en_ud_model-1.1.0/vocab/strings.json
en_ud_model/en_ud_model-1.1.0/vocab/vectors