Metadata-Version: 1.0
Name: en-ud-model
Version: 1.1.0
Summary: ud based model for spacy.
Home-page: https://github/allenai/ud_spacy_model
Author: aryehgigi
Author-email: aryehgigi@gmail.com
License: apache 2.0
Platform: UNKNOWN
